setup.py
Threadripper/Threadripper.py
Threadripper.egg-info/PKG-INFO
Threadripper.egg-info/SOURCES.txt
Threadripper.egg-info/dependency_links.txt
Threadripper.egg-info/top_level.txt