Metadata-Version: 1.0
Name: Threadripper
Version: 0.0.1
Summary: threadpool in processpool
Home-page: https://github.com/gongxiaoze/threadripper
Author: gucheng
Author-email: 1012228022@qq.com
License: UNKNOWN
Platform: UNKNOWN
